twotuft2count/__init__.py
twotuft2count/cli.py
twotuft2count/combine.py
twotuft2count/measure.py
twotuft2count/quantify.py
twotuft2count/segment.py
twotuft2count/visualize.py
twotuft2count-0.1.dist-info/licenses/LICENSE
twotuft2count-0.1.dist-info/METADATA
twotuft2count-0.1.dist-info/WHEEL
twotuft2count-0.1.dist-info/entry_points.txt
twotuft2count-0.1.dist-info/top_level.txt
twotuft2count-0.1.dist-info/RECORD
