Metadata-Version: 2.4
Name: twotuft2count
Version: 0.1
Summary: A CLI pipeline for combining, segmenting, quantifying, and visualizing multiplexed imaging data.
Author: Pascal Flüchter
Author-email: pascal.fluechter@uzh.ch
License-File: LICENSE
Requires-Dist: numpy
Requires-Dist: pandas
Requires-Dist: tifffile
Requires-Dist: scipy
Requires-Dist: napari[all]
Requires-Dist: magicgui
Requires-Dist: click
Requires-Dist: tifftools
Requires-Dist: instanseg-torch
Requires-Dist: fcswrite
Requires-Dist: scikit-image
Dynamic: author
Dynamic: author-email
Dynamic: license-file
Dynamic: requires-dist
Dynamic: summary
